mftpclient/__init__.py
mftpclient/_compat.py
mftpclient/client.py
mftpclient/mptcp_support.py
mftpclient/test/__init__.py
mftpclient/test/test_client.py
mftpclient/test/test_server.py
mftpclient-0.0.3.dist-info/METADATA
mftpclient-0.0.3.dist-info/WHEEL
mftpclient-0.0.3.dist-info/licenses/LICENSE
mftpclient-0.0.3.dist-info/RECORD
