Metadata-Version: 2.1
Name: mftpclient
Version: 0.0.3
Summary: A minimal Multipath TCP client
Project-URL: Homepage, https://github.com/vanyingenzi/mftpclient
Author-email: Ingenzi Vany <ingenzivany@gmail.com>
License-File: LICENSE
Classifier: Development Status :: 1 - Planning
Classifier: Operating System :: POSIX :: Linux
Classifier: Programming Language :: Python :: 3
Classifier: Topic :: Communications :: File Sharing
Classifier: Topic :: Internet :: File Transfer Protocol (FTP)
Requires-Python: >=3.7
